{
    "key": "group_58c03b2ceb66d",
    "title": "Industry Meta",
    "fields": [
        {
            "key": "field_58c03b2cee98f",
            "label": "Industry Field 1",
            "name": "industry_field_1",
            "type": "text",
            "instructions": "",
            "required": 0,
            "conditional_logic": 0,
            "wrapper": {
                "width": "",
                "class": "",
                "id": ""
            },
            "default_value": "",
            "placeholder": "Insert Text",
            "prepend": "",
            "append": "",
            "maxlength": ""
        }
    ],
    "location": [
        [
            {
                "param": "post_type",
                "operator": "==",
                "value": "pbrx_industries"
            }
        ]
    ],
    "menu_order": 0,
    "position": "acf_after_title",
    "style": "default",
    "label_placement": "top",
    "instruction_placement": "field",
    "hide_on_screen": "",
    "active": 1,
    "description": "",
    "modified": 1488993518
}